.gitignore
API.rst
AUTHORS.txt
FlyMovieFormat.mime
LICENSE.txt
README.md
bootstrap.py
fmf-format-spec.rst
fmf-mime.xml
fmf_plottimestamps.desktop
pyproject.toml
requirements.txt
setup.py
stdeb.cfg
.github/workflows/test.yml
fmf2m4v/Makefile
fmf2m4v/SConstruct
fmf2m4v/fmfcompress.c
fmf2m4v/fmfuncompress.c
matlab/fmf_animate.m
matlab/fmf_clip.m
matlab/fmf_frame_count.m
matlab/fmf_get_bits_per_pixel.m
matlab/fmf_get_datatype.m
matlab/fmf_read.m
matlab/fmf_read_frame.m
matlab/fmf_read_header.m
matlab/fmf_write_frame.m
matlab/fmf_write_header.m
matlab/fmf_write_pngs.m
motmot/__init__.py
motmot.FlyMovieFormat.egg-info/PKG-INFO
motmot.FlyMovieFormat.egg-info/SOURCES.txt
motmot.FlyMovieFormat.egg-info/dependency_links.txt
motmot.FlyMovieFormat.egg-info/entry_points.txt
motmot.FlyMovieFormat.egg-info/namespace_packages.txt
motmot.FlyMovieFormat.egg-info/top_level.txt
motmot/FlyMovieFormat/FlyMovieFormat.py
motmot/FlyMovieFormat/__init__.py
motmot/FlyMovieFormat/ffmpeg2fmf.py
motmot/FlyMovieFormat/fmf2bmps.py
motmot/FlyMovieFormat/fmf_collapse.py
motmot/FlyMovieFormat/fmf_info.py
motmot/FlyMovieFormat/fmf_plottimestamps.py
motmot/FlyMovieFormat/fmfcat.py
motmot/FlyMovieFormat/images2fmf.py
motmot/FlyMovieFormat/test_bayer_mono8_bggr.fmf
motmot/FlyMovieFormat/test_mono32f.fmf
motmot/FlyMovieFormat/test_mono8.fmf
motmot/FlyMovieFormat/test_raw8.fmf
motmot/FlyMovieFormat/test_rgb32f.fmf
motmot/FlyMovieFormat/test_rgb8.fmf
motmot/FlyMovieFormat/test_yuv422.fmf
motmot/FlyMovieFormat/tests.py
scripts/fmf_average_frames.py
scripts/fmf_batch_process.py
scripts/fmf_expand_contrast.py
scripts/fmf_subtract_frame.py
scripts/plot_timestamps.py
scripts/pvn2fmf
scripts/truncate_fmf.py