Metadata-Version: 2.1
Name: motmot.FlyMovieFormat
Version: 1.10
Summary: support for .fmf (fly movie format) files
Home-page: http://code.astraw.com/projects/motmot/fly-movie-format.html
Author: Andrew Straw
Author-email: strawman@astraw.com
License: BSD
Platform: UNKNOWN
